{
  "project_info": {
    "project_number": "512593804009",
    "project_id": "crypto-app-flutter-2",
    "storage_bucket": "crypto-app-flutter-2.appspot.com"
  },
  "client": [
    {
      "client_info": {
        "mobilesdk_app_id": "1:512593804009:android:43d2967eed547d4b090e78",
        "android_client_info": {
          "package_name": "com.example.first_app"
        }
      },
      "oauth_client": [
        {
          "client_id": "512593804009-imuhvh3jsbf0m9hj5kmt982irhqit5ad.apps.googleusercontent.com",
          "client_type": 3
        }
      ],
      "api_key": [
        {
          "current_key": "AIzaSyBgrlTO9-3Mb2ht6qpu5AiluQ8wjpFAudE"
        }
      ],
      "services": {
        "appinvite_service": {
          "other_platform_oauth_client": [
            {
              "client_id": "512593804009-imuhvh3jsbf0m9hj5kmt982irhqit5ad.apps.googleusercontent.com",
              "client_type": 3
            }
          ]
        }
      }
    }
  ],
  "configuration_version": "1"
}